inheritance_calculator_core/__init__.py
inheritance_calculator_core/py.typed
inheritance_calculator_core/agents/__init__.py
inheritance_calculator_core/agents/interview_agent.py
inheritance_calculator_core/agents/ollama_client.py
inheritance_calculator_core/agents/prompts.py
inheritance_calculator_core/database/__init__.py
inheritance_calculator_core/database/base.py
inheritance_calculator_core/database/neo4j_client.py
inheritance_calculator_core/database/queries.py
inheritance_calculator_core/database/repositories.py
inheritance_calculator_core/models/__init__.py
inheritance_calculator_core/models/base.py
inheritance_calculator_core/models/inheritance.py
inheritance_calculator_core/models/person.py
inheritance_calculator_core/models/relationship.py
inheritance_calculator_core/services/__init__.py
inheritance_calculator_core/services/base.py
inheritance_calculator_core/services/heir_validator.py
inheritance_calculator_core/services/inheritance_calculator.py
inheritance_calculator_core/services/neo4j_service.py
inheritance_calculator_core/services/share_calculator.py
inheritance_calculator_core/utils/__init__.py
inheritance_calculator_core/utils/config.py
inheritance_calculator_core/utils/era_converter.py
inheritance_calculator_core/utils/exceptions.py
inheritance_calculator_core/utils/logger.py
inheritance_calculator_core-1.0.0.dist-info/METADATA
inheritance_calculator_core-1.0.0.dist-info/WHEEL
inheritance_calculator_core-1.0.0.dist-info/licenses/LICENSE
inheritance_calculator_core-1.0.0.dist-info/RECORD
