Metadata-Version: 2.4
Name: inheritance-calculator-core
Version: 1.0.0
Summary: 日本の民法に基づく相続計算のコアライブラリ
Author-email: Kawahara <your.email@example.com>
License: MIT
License-File: LICENSE
Keywords: calculator,core,inheritance,japan,law,neo4j
Classifier: Development Status :: 4 - Beta
Classifier: Intended Audience :: Developers
Classifier: Intended Audience :: Legal Industry
Classifier: License :: OSI Approved :: MIT License
Classifier: Programming Language :: Python :: 3.12
Classifier: Topic :: Office/Business
Classifier: Topic :: Software Development :: Libraries
Requires-Python: >=3.12
Requires-Dist: neo4j~=6.0.2
Requires-Dist: pydantic-settings~=2.11.0
Requires-Dist: pydantic[email]~=2.11.9
Requires-Dist: python-dotenv~=1.1.1
Provides-Extra: agents
Requires-Dist: agnos~=1.0.2; extra == 'agents'
Requires-Dist: ollama~=0.6.0; extra == 'agents'
Provides-Extra: dev
Requires-Dist: black>=24.0.0; extra == 'dev'
Requires-Dist: mypy~=1.8.0; extra == 'dev'
Requires-Dist: pytest-cov~=4.0.0; extra == 'dev'
Requires-Dist: pytest~=8.0.0; extra == 'dev'
Requires-Dist: ruff~=0.1.0; extra == 'dev'
